tbpy/__init__.py
tbpy/test.py
tbpy-1.3.1.1.dist-info/LICENSE
tbpy-1.3.1.1.dist-info/METADATA
tbpy-1.3.1.1.dist-info/WHEEL
tbpy-1.3.1.1.dist-info/top_level.txt
tbpy-1.3.1.1.dist-info/RECORD
