Metadata-Version: 2.1
Name: tbpy
Version: 1.3.1.1
Summary: Welcome to terminalbreaker
Home-page: https://github.com/Ellicode/terminalbreaker
Author: Ellicode
Author-email: Ellicode <ellicode22@gmail.com>
Project-URL: Homepage, https://github.com/Ellicode/terminalbreaker
Project-URL: Bug Tracker, https://github.com/Ellicode/terminalbreaker/issues
Classifier: Programming Language :: Python :: 3
Classifier: License :: OSI Approved :: MIT License
Classifier: Operating System :: OS Independent
Requires-Python: >=3.6
License-File: LICENSE
